sphinxcontrib/t3tablerows.py
sphinxcontrib/__init__.py
t3tablerows-0.1.0.dist-info/DESCRIPTION.rst
t3tablerows-0.1.0.dist-info/WHEEL
t3tablerows-0.1.0.dist-info/metadata.json
t3tablerows-0.1.0.dist-info/METADATA
t3tablerows-0.1.0.dist-info/top_level.txt
t3tablerows-0.1.0.dist-info/RECORD
