Metadata-Version: 2.0
Name: t3tablerows
Version: 0.1.0
Summary: Implement Sphinx transformation of "table-row" containers
Home-page: https://github.com/TYPO3-Documentation/sphinxcontrib.t3tablerows
Author: Martin Bless
Author-email: martin@mbless.de
License: BSD
Keywords: sphinx extension transformation
Platform: UNKNOWN
Classifier: Development Status :: 5 - Production/Stable
Classifier: Intended Audience :: End Users/Desktop
Classifier: Framework :: Sphinx :: Extension
Classifier: License :: OSI Approved :: BSD License
Classifier: Programming Language :: Python :: 2
Classifier: Programming Language :: Python :: 3
Classifier: Operating System :: OS Independent
Classifier: Topic :: Documentation
Requires-Dist: sphinx
